guetwifi/cli.py
guetwifi/guetwifirunner.py
guetwifi-0.1.7.dist-info/METADATA
guetwifi-0.1.7.dist-info/WHEEL
guetwifi-0.1.7.dist-info/entry_points.txt
guetwifi-0.1.7.dist-info/RECORD
