Metadata-Version: 2.1
Name: guetwifi
Version: 0.1.7
Summary: GUET WiFi Monitor
Home-page: https://github.com/andPuQing/guetwifi
License: MIT
Author: PuQing
Author-email: me@puqing.work
Requires-Python: >=3.7,<4.0
Classifier: Environment :: Console
Classifier: Intended Audience :: End Users/Desktop
Classifier: License :: OSI Approved :: MIT License
Classifier: Programming Language :: Python
Classifier: Programming Language :: Python :: 3
Classifier: Programming Language :: Python :: 3.7
Classifier: Programming Language :: Python :: 3.8
Classifier: Programming Language :: Python :: 3.9
Classifier: Programming Language :: Python :: 3.10
Classifier: Programming Language :: Python :: 3.11
Classifier: Programming Language :: Python :: 3.12
Classifier: Topic :: System :: Networking
Requires-Dist: click (>=8.0.0,<9.0.0)
Requires-Dist: psutil (>=5.7.2,<6.0.0)
Requires-Dist: requests (>=2.23.0,<3.0.0)
Project-URL: Repository, https://github.com/andPuQing/guetwifi.git
